sai_rl/__init__.py
sai_rl/error.py
sai_rl/py.typed
sai_rl/sai_client.py
sai_rl/sai_console.py
sai_rl/api/__init__.py
sai_rl/api/client.py
sai_rl/api/requestor.py
sai_rl/api/requestor_options.py
sai_rl/api/routes/competition.py
sai_rl/api/routes/environment.py
sai_rl/api/routes/package.py
sai_rl/api/routes/scene.py
sai_rl/api/routes/submission.py
sai_rl/benchmark/__init__.py
sai_rl/benchmark/benchmark.py
sai_rl/benchmark/blur.py
sai_rl/benchmark/jpeg_artifact.py
sai_rl/benchmark/noise.py
sai_rl/benchmark/record.py
sai_rl/benchmark/seed.py
sai_rl/benchmark/types.py
sai_rl/benchmark/utils.py
sai_rl/env/__init__.py
sai_rl/env/custom_eval.py
sai_rl/env/environment.py
sai_rl/model/__init__.py
sai_rl/model/model_manager.py
sai_rl/model/custom/__init__.py
sai_rl/model/custom/action_manager.py
sai_rl/model/custom/custom_code_manager.py
sai_rl/model/custom/preprocessing_manager.py
sai_rl/model/handlers/__init__.py
sai_rl/model/handlers/_base.py
sai_rl/model/handlers/keras.py
sai_rl/model/handlers/onnx.py
sai_rl/model/handlers/pytorch.py
sai_rl/model/handlers/sb3.py
sai_rl/model/handlers/tensorflow.py
sai_rl/package/__init__.py
sai_rl/package/package_control.py
sai_rl/types/__init__.py
sai_rl/types/competition.py
sai_rl/types/environment.py
sai_rl/types/package.py
sai_rl/types/scene.py
sai_rl/types/submission.py
sai_rl/types/task.py
sai_rl/utils/__init__.py
sai_rl/utils/config.py
sai_rl/utils/log_capture.py
sai_rl/utils/optional_deps.py
sai_rl/utils/server.py
sai_rl-0.1.37.dist-info/METADATA
sai_rl-0.1.37.dist-info/WHEEL
sai_rl-0.1.37.dist-info/licenses/LICENSE
sai_rl-0.1.37.dist-info/RECORD
